{
    "发票登记台账": [
        {
            "序号": "1",
            "发票号码": "7894561",
            "对方单位名称": "杭州大华电子有限公司",
            "纳税人识别号": "913301001530621847",
            "发票代码": "33220014",
            "开票日期": "2020-04-1500:00:00",
            "不含税金额": "3846.15",
            "税率": "0.13",
            "税额": "653.85",
            "开票金额": "4500",
            "发票类型": "普通发票",
            "备注": "None"
        },
        {
            "序号": "2",
            "发票号码": "0894562",
            "对方单位名称": "花儿有限责任公司",
            "纳税人识别号": "913301001530621125",
            "发票代码": "33226615",
            "开票日期": "2020-04-1600:00:00",
            "不含税金额": "5825.24",
            "税率": "0.03",
            "税额": "174.76",
            "开票金额": "6000",
            "发票类型": "专用发票",
            "备注": "None"
        },
        {
            "序号": "3",
            "发票号码": "1894563",
            "对方单位名称": "小熊猫有限公司",
            "纳税人识别号": "9133010015306234567",
            "发票代码": "33229916",
            "开票日期": "2020-05-1700:00:00",
            "不含税金额": "4273.5",
            "税率": "0.13",
            "税额": "726.5",
            "开票金额": "5000",
            "发票类型": "电子发票",
            "备注": "None"
        },
        {
            "序号": "4",
            "发票号码": "7894562",
            "对方单位名称": "杭州大华电子有限公司",
            "纳税人识别号": "913301001530621847",
            "发票代码": "33220014",
            "开票日期": "2020-05-1800:00:00",
            "不含税金额": "3846.15",
            "税率": "0.13",
            "税额": "653.85",
            "开票金额": "4500",
            "发票类型": "普通发票",
            "备注": "None"
        },
        {
            "序号": "5",
            "发票号码": "0894564",
            "对方单位名称": "花儿有限责任公司",
            "纳税人识别号": "913301001530621125",
            "发票代码": "33226615",
            "开票日期": "2020-06-1900:00:00",
            "不含税金额": "5825.24",
            "税率": "0.03",
            "税额": "174.76",
            "开票金额": "6000",
            "发票类型": "专用发票",
            "备注": "None"
        },
        {
            "序号": "6",
            "发票号码": "1894566",
            "对方单位名称": "小熊猫有限公司",
            "纳税人识别号": "9133010015306234567",
            "发票代码": "33229916",
            "开票日期": "2020-06-2000:00:00",
            "不含税金额": "4273.5",
            "税率": "0.13",
            "税额": "726.5",
            "开票金额": "5000",
            "发票类型": "电子发票",
            "备注": "None"
        }
    ]
}